{
  "gitSyncId": "68b6a06fbe3e98727f730e44_a2b61ad5-2548-42a3-9b81-12a94c326091",
  "id": "Page1_getUniqueGenders",
  "pluginId": "postgres-plugin",
  "pluginType": "DB",
  "unpublishedAction": {
    "actionConfiguration": {
      "body": "SELECT DISTINCT gender FROM public.\"users\";",
      "encodeParamsToggle": true,
      "paginationType": "NONE",
      "pluginSpecifiedTemplates": [
        {
          "value": true
        }
      ],
      "timeoutInMillisecond": 10000
    },
    "confirmBeforeExecute": false,
    "datasource": {
      "id": "Users",
      "isAutoGenerated": false,
      "name": "Users",
      "pluginId": "postgres-plugin"
    },
    "dynamicBindingPathList": [],
    "name": "getUniqueGenders",
    "pageId": "Page1",
    "runBehaviour": "ON_PAGE_LOAD",
    "userSetOnLoad": true
  }
}